{"assertionCriteria": {"method": "ClinGen PAH ACMG Specifications v1", "citation": {"url": "https://submit.ncbi.nlm.nih.gov/ft/byid/i2ra5ppm/clingen_pah_acmg_specifications_v1.pdf"}}, "clinicalSignificance": {"citation": [{"url": "https://erepo.clinicalgenome.org/evrepo/ui/interpretation/b8a375eb-ab64-4ae6-9596-fb9df15defac"}], "clinicalSignificanceDescription": "Pathogenic", "comment": "This variant c.740del (p.Gly247AlafsTer?) in PAH was reported 1 time in a patient with PAH deficiency in the Czech Republic (PMID 23357515). This is a frameshift variant in exon 7 out of 13 coding exons, predicted to undergo nonsense mediated mRNA decay. The exon is present in biologically-relevant transcripts. This variant is absent in population databases. In summary, this variant meets criteria to be classified as pathogenic for PAH. PAH-specific ACMG/AMP criteria applied: PVS1, PM2, PP4", "dateLastEvaluated": "2020-11-24", "modeOfInheritance": "Autosomal recessive inheritance"}, "conditionSet": {"condition": [{"db": "MONDO", "id": "MONDO:0009861"}]}, "localID": "b8a375eb-ab64-4ae6-9596-fb9df15defac", "localKey": "b8a375eb-ab64-4ae6-9596-fb9df15defac", "observedIn": [{"collectionMethod": "curation", "alleleOrigin": "germline", "affectedStatus": "unknown", "numberOfIndividuals": 0}], "recordStatus": "novel", "releaseStatus": "public", "variantSet": {"variant": [{"gene": [{"symbol": "PAH"}], "hgvs": "NC_000012.12:g.102852918del"}]}}